pyegen/__init__.py
pyegen/core.py
pyegen-0.2.4.dist-info/licenses/LICENSE
pyegen-0.2.4.dist-info/METADATA
pyegen-0.2.4.dist-info/WHEEL
pyegen-0.2.4.dist-info/top_level.txt
pyegen-0.2.4.dist-info/RECORD
