Metadata-Version: 2.4
Name: pyegen
Version: 0.2.4
Summary: Python implementation of Stata's egen command for pandas DataFrames
Author-email: Bryce Wang <brycew6m@stanford.edu>
License: MIT
Project-URL: Homepage, https://github.com/brycewang-stanford/pyegen
Project-URL: Documentation, https://github.com/brycewang-stanford/pyegen/blob/main/README.md
Project-URL: Repository, https://github.com/brycewang-stanford/pyegen
Project-URL: Bug Tracker, https://github.com/brycewang-stanford/pyegen/issues
Keywords: stata,egen,pandas,data-analysis,econometrics,statistics
Classifier: Development Status :: 4 - Beta
Classifier: Intended Audience :: Science/Research
Classifier: License :: OSI Approved :: MIT License
Classifier: Operating System :: OS Independent
Classifier: Programming Language :: Python :: 3
Classifier: Programming Language :: Python :: 3.7
Classifier: Programming Language :: Python :: 3.8
Classifier: Programming Language :: Python :: 3.9
Classifier: Programming Language :: Python :: 3.10
Classifier: Programming Language :: Python :: 3.11
Classifier: Programming Language :: Python :: 3.12
Classifier: Programming Language :: Python :: 3.13
Classifier: Topic :: Scientific/Engineering
Classifier: Topic :: Software Development :: Libraries :: Python Modules
Requires-Python: >=3.7
License-File: LICENSE
Requires-Dist: pandas>=1.3.0
Requires-Dist: numpy>=1.20.0
Provides-Extra: dev
Requires-Dist: pytest>=7.0.0; extra == "dev"
Requires-Dist: pytest-cov>=4.0.0; extra == "dev"
Requires-Dist: black>=22.0.0; extra == "dev"
Requires-Dist: isort>=5.10.0; extra == "dev"
Requires-Dist: flake8>=5.0.0; extra == "dev"
Requires-Dist: mypy>=0.990; extra == "dev"
Requires-Dist: build>=0.8.0; extra == "dev"
Requires-Dist: twine>=4.0.0; extra == "dev"
Dynamic: license-file
